fairchem/lammps/LICENSE.md
fairchem/lammps/README.md
fairchem/lammps/__init__.py
fairchem/lammps/lammps_fc.py
fairchem/lammps/lammps_fc_config.yaml
fairchem/lammps/lammps_in_example.file
fairchem_lammps-0.3.0.dist-info/METADATA
fairchem_lammps-0.3.0.dist-info/WHEEL
fairchem_lammps-0.3.0.dist-info/entry_points.txt
fairchem_lammps-0.3.0.dist-info/RECORD
