Metadata-Version: 2.4
Name: fairchem-lammps
Version: 0.3.0
Summary: Fairchem extension package to use LAMMPs with fairchem models
Project-URL: repository, https://github.com/facebookresearch/fairchem
Project-URL: home, https://opencatalystproject.org/
Project-URL: documentation, https://fair-chem.github.io/
License: GnuV2 License
Requires-Python: <3.13,>=3.10
Requires-Dist: fairchem-core>=2.4.0
